[
  {
    "id": "a001",
    "type": "single",
    "topic": "指對數",
    "question": "設 a = log2, b = log3。若 10^x = 3/2，則 x 之值為何？",
    "options": ["A) b-a", "B) a-b", "C) a/b", "D) b/a"],
    "answer": "A"
  },
  {
    "id": "a001",
    "type": "single",
    "topic": "平面向量",
    "question": "設 A(1, 2), B(4, 6), C(x, y)且x > 0。若向量 AB 與向量 AC 垂直 且|AC|=5，則 x 可能為多少？",
    "options": ["A) 5", "B) 6", "C) 7", "D) 9"],
    "answer": "A"
  },
  {
    "id": "a002",
    "type": "single",
    "topic": "機率",
    "question": "袋中有 3 紅球 2 白球。從中隨機取球，每次取一球不放回，連取兩次。已知第二次取到紅球的條件下，第一次也取到紅球的機率為何？",
    "options": ["A) 1/2", "B) 2/3", "C) 3/5", "D) 1/5"],
    "answer": "A"
  },
  {
    "id": "a003",
    "type": "single",
    "topic": "數列",
    "question": "一等差數列前 10 項和為 100，前 20 項和為 400，則前 30 項和為何？",
    "options": ["A) 700", "B) 800", "C) 900", "D) 1000"],
    "answer": "C"
  },
  {
    "id": "a004",
    "type": "single",
    "topic": "三角函數",
    "question": "在三角形 ABC 中，a=7, b=8, c=9，則 cos A = ?",
    "options": ["A) 2/3", "B) 11/21", "C) 1/2", "D) 14/19"],
    "answer": "A"
  },
  {
    "id": "a005",
    "type": "multiple",
    "topic": "多項式",
    "question": "設 f(x) 為實係數三次多項式。已知 f(1)=f(2)=0 且 f(3)=4, f(0)=2。下列敘述哪些正確？",
    "options": ["A) f(x) 有 (x-1) 之因式", "B) f(x) 的領導係數為 1", "C) f(4) = 12", "D) f(x) 除以 (x-1)(x-2) 的餘式為 0"],
    "answer": "ABD"
  },
  {
    "id": "a006",
    "type": "multiple",
    "topic": "數據分析",
    "question": "若一組數據的標準差為 0，則下列哪些正確？",
    "options": ["A) 平均數等於中位數", "B) 全距為 0", "C) 所有數據皆相等", "D) 算術平均數為 0"],
    "answer": "ABC"
  },{
    "id": "a007",
    "type": "multiple",
    "topic": "直線與圓",
    "question": "圓 C: x^2+y^2=4 與直線 L: x+y=k 相交，則 k 可能為？",
    "options": ["A) 0", "B) 1", "C) 2", "D) 3", "E) -1"],
    "answer": "ABC"
  },
  {
    "id": "a008",
    "type": "multiple",
    "topic": "空間幾何",
    "question": "空間中，下列何者可確定一平面？",
    "options": ["A) 不共線三點", "B) 一直線與線外一點", "C) 兩平行線", "D) 兩歪斜線"],
    "answer": "ABC"
  },
  {
    "id": "a009",
    "type": "math",
    "topic": "排列組合",
    "question": "將「success」七字母全排列，三 s 不完全相鄰排法共有幾種？",
    "options": [],
    "answer": "360"
  },
  {
    "id": "a010",
    "type": "multiple",
    "topic": "指對數",
    "question": "關於 y = 2^x 的圖形，下列敘述哪些正確？",
    "options": ["A) 通過 (0,1)", "B) 恆在 x 軸上方", "C) 是增函數", "D) 與 y=x 有交點"],
    "answer": "ABC"
  },
  {
    "id": "a011",
    "type": "math",
    "topic": "三角函數",
    "question": "已知 sin x + cos x = 1.2，則 sin x * cos x = ? (填小數)",
    "options": [],
    "answer": "0.22"
  },
  {
    "id": "a012",
    "type": "math",
    "topic": "平面向量",
    "question": "向量 u=(2,1), v=(x,-4)。若 u 垂直 v，則 x = ?",
    "options": [],
    "answer": "2"
  },
  {
    "id": "a013",
    "type": "math",
    "topic": "數據分析",
    "question": "數據 1, 3, 5, 7, 9 的標準差平方（變異數）為何？",
    "options": [],
    "answer": "8"
  },
  {
    "id": "a014",
    "type": "math",
    "topic": "三角函數",
    "question": "在三角形ABC中，已知 AB=5, BC=7, CA=8。求此三角形的最大內角角度的餘弦值為何？",
    "options": [],
    "answer": "1/7"
  },
  {
    "id": "a015",
    "type": "single",
    "topic": "機率",
    "question": "財神廟舉辦抽發財金活動：參加者抽兩次籤，每次抽籤出現「吉」、「祥」的機率皆為1/3。如果兩次都抽得「吉」，獲得獎金180元；如果兩次都抽得「祥」，獲得獎金90元；其餘情況則無獎金。試問參加者可獲獎金的期望值為何？",
    "options": ["A) 20元", "B) 30元", "C) 45元", "D) 60元", "E) 90元"],
    "answer": "B"
  },
  {
    "id": "a016",
    "type": "single",
    "topic": "多項式",
    "question": "對任一實數a，令[a]代表滿足[a] ≤ a < [a]+1的整數，例如：[3] = 3，[3.1] = 3，[-3.1] = -4。關於函數f(x) =[√(99-x)]+[√(99+x)]，其中 -99 ≤ x ≤ 99；試選出正確的選項。",
    "options": ["A) f(-20) ≤ f(0) < f(1)", "B) f(-20) < f(0) ≤ f(1)", "C) f(1) < f(-20) ≤ f(0)", "D) f(0) < f(-20) ≤ f(1)", "E) f(0) ≤ f(1) ≤ f(20)"],
    "answer": "A"
  },
  {
    "id": "a017",
    "type": "single",
    "topic": "指對數",
    "question": "設f(x) = a^x，其中a為正整數。已知c1, c2, c3是公差為10/3的等差數列，且f(c1), f(c2), f(c3)是公比為4的等比數列，則f(10), f(8), f(6)的公比是？",
    "options": ["A) 2^(-6/5)", "B) 2^(-3/5)", "C) 2^(3/5)", "D) 2^(6/5)", "E) 2^(5/3)"],
    "answer": "A"
  },
  {
    "id": "a018",
    "type": "math",
    "topic": "排列組合",
    "question": "某網遊有6種基本、10種進階材料。任選3種不同材料可以合成出道具，若3種材料均為基本，則合成結果必為同一種；若3種材料中2種為基本，1種為進階，則結果會根據不同的進階材料不同，但不受基本不同改變；其他組合都會合成出不同種的道具。試問此網遊總共可合成出多少種道具？",
    "options": [],
    "answer": "401"
  },
  {
    "id": "a019",
    "type": "single",
    "topic": "矩陣",
    "question": "已知實數三階方陣A滿足A[1, 1, 0] = [0, -1, 1]，A[0, -1, 1] = [1, 1, 0], A[1, 0, -1] = [0, 0, 0]。試問有多少個行向量v = [v1, v2, v3]滿足Av = [1, 0, 1]且向量v垂直於行向量[0, 1, 0]？",
    "options": ["A) 1個", "B) 2個", "C) 3個", "D) 0個", "E) 無窮多個"],
    "answer": "E"
  },
  {
    "id": "a020",
    "type": "math",
    "topic": "平面幾何",
    "question": "坐標平面上有A(2, -2)、B(-1, 2)兩點，試問直線 y = -6上有多少個點C使得△ABC為等腰三角形？",
    "options": [],
    "answer": "2"
  },
  {
    "id": "a021",
    "type": "multiple",
    "topic": "不等式",
    "question": "在標平面上同時滿足2x-y-3>0、x+2y<-1的點P(x, y)可能位於下列哪些選項？",
    "options": ["A) 第一象限", "B) 第二象限", "C) 第三象限", "D) 第四象限", "E) x軸"],
    "answer": "CD"
  },
  {
    "id": "a022",
    "type": "multiple",
    "topic": "平面向量",
    "question": "已知四邊形ABCD中，AB // DC，AC與BD交於E，若向量AB = (2, -6), 向量AD = (1, 5)且△ABE面積為3，試選出正確的選項。",
    "options": ["A) cosBAD = (-7√65)/65", "B) △ABD面積為9", "C) 向量AE = (3/2, 1/2)", "D) 四邊形ABCD面積為65/3", "E) BC < 8/3"],
    "answer": "AE"
  },
  {
    "id": "a023",
    "type": "math",
    "topic": "機率",
    "question": "某高中聘用的全體教師1/4只有學士學位，3/4有碩士學位。只學士學位的教師中有1/5通過英聽檢定，有碩士學位的教師中有3/5通過英聽檢定。已知每位教師被抽到的機會相等，若隨機抽選一位通過英聽檢定的教師，則該教師有碩士學位的條件機率為？（化為最簡分數）",
    "options": [],
    "answer": "9/10"
  },
  {
    "id": "a024",
    "type": "math",
    "topic": "平面向量",
    "question": "坐標平面上，向量(a, b)與直線y=bx-1垂直，則a+b最大可能值為？（化為最簡分數）",
    "options": [],
    "answer": "1/4"
  },
  {
    "id": "a025",
    "type":"math",
    "topic": "數列",
    "question": "已知3正數a, b, c成一等差數列，其中a < b < c，且座標平面上3個點(a, log3a)、(b, log4b)、(c, log6c)在同一直線上，則b/a之值為？（化為最簡分數）",
    "options": [],
    "answer": "3/2"
  },
  {
    "id": "a026",
    "type": "math",
    "topic": "二次函數",
    "question": "坐標平面上，已知二次函數圖形Γ: y = f(x)的頂點P在直線y=1+2x上，且交x軸於A(-1/2, 0)、B(1/2, 0)，將Γ平移使得平移後圖形的頂點Q仍在直線y = 1+2x上，且亦通過B點，此時P、Q為兩相異點，若PQ = (s √t )/u，則s+t+u=？",
    "options": [],
    "answer": "10"
  },
  {
    "id": "a027",
    "type": "math",
    "topic": "三角函數",
    "question": "直角三角形△ABC中，∠CAB為直角，AB邊上一點D，滿足∠BCD = 2∠ACD，且BC=2BD。若向量AD = k倍向量AB，則k=？（化為最簡分數）",
    "options": [],
    "answer": "11/3"
  },
  {
    "id": "a028",
    "type": "single",
    "topic": "機率",
    "question": "不透明袋中有藍、綠色球各若干顆，且球上皆有1或2的編號，其顆為：標有1號的藍色球有2顆，2號藍色球有3顆，1號綠色球有4顆，2號綠色球有k顆。從此袋中隨機抽取一球（每顆球被抽到的機率相等），若已知抽到藍色球的事件與抽到1號球的事件互相獨立，試問k值為何？",
    "options": ["A) 2", "B) 3", "C) 4", "D) 5", "E) 6"],
    "answer": "E"
  },
  {
    "id": "a029",
    "type": "single",
    "topic": "直線與圓",
    "question": "坐標平面上，P(a, 0)為x軸上一點，其中a > 0。令L1、L2為通過P點，斜率分別為-4/3、-3/2的直線。已知L1、L2分別與兩坐標軸圍成的兩個直角三角形的面積差為3，試問a值為何？",
    "options": ["A) 3√2", "B) 6", "C) 6√2", "D) 9", "E) 8√2"],
    "answer": "B"
  },
  {
    "id": "a030",
    "type": "single",
    "topic": "排列組合",
    "question": "某校舉辦音樂會，包含鋼琴表演5個、小提琴表演4個、歌唱表演3個等三類表演共12個不同曲目。該校想將同類表演排在一起，且歌唱必須排在鋼琴之後或是小提琴之後。試問這場音樂會可能的曲目排列方式共有幾種？",
    "options": ["A) 5!4!3!", "B) 2*5!4!3!", "C) 3*5!4!3!", "D) 4*5!4!3!", "E) 6*5!4!3!"],
    "answer": "D"
  },
  {
    "id": "a031",
    "type": "single",
    "topic": "指對數",
    "question": "坐標平面上，x坐標與y坐標均為整數的點稱為格子點。試問在函數圖形y = log₂x、x軸與直線x = 61/2所圍有界區域的內部（不含邊界）共有多少個格子點？",
    "options": ["A) 88", "B) 89", "C) 90", "D) 91", "E) 92"],
    "answer": "C"
  },
  {
    "id": "a032",
    "type": "single",
    "topic": "三角函數",
    "question": "設0 < θ < 2π。已知所有滿足sin2θ > sinθ且cos2θ > cosθ的θ可表為aπ < θ < bπ， 其中a,b為實數，試問b - a值為何？",
    "options": ["A) 1/3", "B) 1/2", "C) 2/3", "D) 3/4", "E) 1"],
    "answer": "A"
  },
  {
    "id": "a033",
    "type": "single",
    "topic": "空間向量",
    "question": "坐標空間中有三個彼此互相垂直之向量u, v, w，已知向量u-v = (2, -1, 0)，且向量v-w = (-1, 2, 3)。試問由向量u、v、w所張出的平行六面體之體積為何？",
    "options": ["A) 2√5", "B) 5√2", "C) 2√10", "D) 4√5", "E) 4√10"],
    "answer": "C"
  },
  {
    "id": "a034",
    "type": "multiple",
    "topic": "數列",
    "question": "已知數列<a(n)>滿足3a(n+1) = a(n) + n（對任意正整數n都成立）且a₁=2。另數列<b(n)>滿足b(n) = a(n) - n/2 + 3/4。試選出正確的選項。",
    "options": ["A) a₂ = 2", "B) b₂ = 3/4", "C) 數列<b(n)>是公比為2/3的等比數列", "對於任意正整數n，3ⁿa(n)皆為正整數", "E) b₁₀ < 10⁴"],
    "answer": "BD"
  },
  {
    "id": "a035",
    "type": "multiple",
    "topic": "直線與圓",
    "question": "考慮坐標平面上滿足方程式(2^x^2) / 8 = (4^x) / (2^y^2)的點P(x, y)，試選出正確的選項。",
    "options": ["A) 當x = 3時，滿足此方程式的解有相異2個", "B) 若點(a, b)滿足此方程式，則點(-a, -b)也滿足此方程式", "C) 所有可能的點P(x, y)構成的圖行為一個圓", "D) P(x, y)可能在直線x + y = 4上", "E) 對於所有可能的點P(x, y)，其x-y的最大值為1+2√2"],
    "answer": "CE"
  },
  {
    "id": "a036",
    "type": "multiple",
    "topic": "二次函數",
    "question": "設b、c為實數，已知二次方程式x²+bx+c = 0有實根，但二次函數x²+(b+2)x+c = 0沒有實根。試選出正確的選項。",
    "options": ["A) c < 0", "B) b < 0", "C) x²+(b+1)x+c = 0有實根", "D) x²+(b+2)x+c = 0有實根", "E) x²+(b-2)x+c = 0有實根"],
    "answer": "BDE"
  },
  {
    "id": "a037",
    "type": "multiple",
    "topic": "三角函數",
    "question": "令Γ為坐標平面上y = sinπx=在0 ≤ x ≤ 3內之函數圖形。一水平直線L: y = k與Γ相交，其中三交點P(x1, k)、Q(x2, k)、R(x3, k)滿足x1 < x2 < 1 < x3。試選出正確的選項：",
    "options": ["A) k > 0", "B) L與Γ恰有3個交點", "C) x1 + x2 < 1", "D) 若2PQ = QR，則k = 1/2", "E) L與Γ所有交點的x座標之和大於5"],
    "answer": "ADE"
  },
  {
    "id": "a038",
    "type": "math",
    "topic": "多項式",
    "question": "已知實係數三次多項式f(x)除以x+6得商式q(x)和餘式3。若q(x)在x = -6有最大值8，則f(x)圖形的對稱中心坐標為(a, b)，求ab之值",
    "options": [],
    "answer": "-18"
  },
  {
    "id": "a039",
    "type": "math",
    "topic": "空間幾何",
    "question": "坐標空間中，已知點A的坐標為(a, b, c)，其中a, b, c皆為小於0的實數，且知點A與三平面E1: 4y+3z=2、E2: 3y+4z=-5、E3: x+2y+2z=-2的距離都是6，則a+b+c=？",
    "options": [],
    "answer": "-11"
  },
  {
    "id": "a040",
    "type": "math",
    "topic": "機率",
    "question": "有一活動規則為：投擲一枚均勻硬幣至多5次，前3次連續擲得3個正面者則能以240元購得一個玩偶，擲到第4次才累積得3個正面者則只能以320元購得一個，擲到第5次者則只能以400元購得一個；5次投完仍未累積3個正面者則只能以480元購得。顧客購得一個玩偶所花金額的期望值為？",
    "options": [],
    "answer": "405"
  },
  {
    "id": "a041",
    "type": "math",
    "topic": "直線與圓",
    "question": " 坐標平面上，設L1、L2為通過(3, 1)且斜率分別為m、-m的兩條直線，其中m為一實數。另設Γ為圓心在原點的一個圓。已知Γ與L1交於相異兩點A、B，且知圓心到L1的距離為1，又Γ與L2相切，則弦AB的長度為？（化為最簡分數）",
    "options": [],
    "answer": "24/5"
  },
  {
    "id": "a042",
    "type": "math",
    "topic": "三角函數",
    "question": "△ABC中，已知AB = BC = 3，cos∠ABC = -1/8，在△ABC的外接圓上有一點D滿足BD = 4，且AD ≤ CD，則CD = a + √b，求a/b（化為最簡根式及最簡分數）",
    "options": [],
    "answer": "3/2"
  },
  {
    "id": "a043",
    "type": "single",
    "topic": "多項式",
    "question": "設a∈{-6, -4, -2, 2, 4, 6}，已知a為實係數三次多項式f(x)的最高次項係數，若函數f(x)的圖形與x軸交於三點，且其x坐標成首項為-7、公差為a的等差數列。試問共有幾個a使得f(0) > 0？",
    "options": ["A) 1個", "B) 2個", "C) 3個", "D) 4個", "E) 5個"],
    "answer": "A"
  },
  {
    "id": "a044",
    "type": "single",
    "topic": "三角函數",
    "question": "試問有多少的實數x滿足sin(x + π/6) = sinx + sin(π/6) 且 0 ≤ x < 2π？",
    "options": ["A) 1個", "B) 2個", "C) 3個", "D) 4個", "E) 5個以上"],
    "answer": "B"
  },
  {
    "id": "a045",
    "type": "single",
    "topic": "排列組合",
    "question": "將1到50這50個正整數平分成甲乙兩組，每組各25個數，使得甲組的中位數比乙組的中位數小1。試問共有幾種分法？",
    "options": ["A) C(50, 25)", "B) C(48, 24)", "C) C(24, 12)", "D) (C(24, 12))^2", "E) C(48, 24)*C(24, 12)"],
    "answer": "D"
  },
  {
    "id": "a046",
    "type": "single",
    "topic": "三角函數",
    "question": "在同一平面上，相距7公里的AB兩砲台，A在B的正東方。A向西偏北θ方向發射砲彈，B則向東偏北θ方向發射砲彈，其中θ為銳角，兩砲彈皆命中9公里外的同一目標P。接著A改向西偏北θ/2方向發射砲彈，彈著點為9公里外的點Q。試問BQ長為何？",
    "options": ["A) 4km", "B) 4.5km", "C) 5km", "D) 5.5km", "E) 6km"],
    "answer": "C"
  },
  {
    "id": "a047",
    "type": "multiple",
    "topic": "指對數",
    "question": "令坐標平面上滿足y = logx的點(x, y)所形成的圖形為Γ，試問滿足下列哪些關係式的(x, y)所成圖形與Γ完全相同？",
    "options": ["A) y + 1/2 = log(5x)", "B) 2y = log(x^2)", "C) 3y = log(x^3)", "D) x = 10^y", "E) x^3 = 10^y^3"],
    "answer": "CD"
  },
  {
    "id": "a048",
    "type": "multiple",
    "topic": "平面幾何",
    "question": "對任一正整數2 <= n，令Tn表示邊長為n, n+1, n+2的三角形。試選出正確的選項。",
    "options": ["A) Tn皆為銳角三角形", "B) T2, T3, T4, ..., T10的周長形成等差數列", "C) Tn的面積會隨n增大而增大", "D) T5的三高形成等差數列", "E) T3的最大角大於T2的最大角"],
    "answer": "BC"
  },
  {
    "id": "a049",
    "type": "multiple",
    "topic": "平面幾何",
    "question": "坐標平面上有一正方形與一正六邊形，正方形在正六邊形的右邊。已知兩正多邊形都有一邊在x軸上，且正方形中心A與正六邊形中心B都在x軸的上方，且兩多邊形恰有一個交點P，又知正方形的邊長為6，而點P到x軸的距離為2√3。試選出正確的選項。",
    "options": ["A) A到x軸的距離大於B到x軸的距離", "B) 正六邊形邊長為6", "C) 向量BA = (7, 3-2√3)", "D) AP > √10", "E) 直線AP斜率大於-1/√3"],
    "answer": "CE"
  },
  {
    "id":"a050",
    "type": "multiple",
    "topic": "機率",
    "question": "二元一次方程組ax+6y=6、x+by=1，其係數a, b之值分別由投擲一顆公正骰子與一枚均勻硬幣來決定。令a值為骰子出現之點數；若硬幣出現正面時b值為1，若硬幣出現反面時b值為2。試選出正確的選項",
    "options": ["擲出a=b的機率為1/3", "B) 此方程組無解的機率為1/12", "C) 此方程組有唯一解的機率為5/6", "D) 硬幣出現反面且此方程組有解的機率為1/3", "E) 在硬幣出現反面且此方程組有解的條件下，x值為正的機率為2/5"],
    "answer": "BC"
  },
  {
    "id": "a051",
    "type": "math",
    "topic": "數據分析",
    "question": "某銷售站銷售甲、乙、丙三型手機，甲手機每支利潤100，乙手機每支利潤400，丙手機每支利潤240。上年度甲、乙、丙手機各賣出A, B, C支，平均每支利潤為260；且知銷售甲、乙兩型手機共A+B支的平均每支利潤為280。則A:B:C = ?（最簡整數比）",
    "options": [],
    "answer": "2:3:5"
  },
  {
    "id": "a052",
    "type": "math",
    "topic": "多項式",
    "question": "已知f(x)、g(x)、h(x)皆為實係數三次多項式，且除以x²-2x+3的餘式分別為x+1、x-3、-2。若xf(x) + ag(g) + bh(x)可以被x²-2x+3整除，a, b為實數，則(a,b) = ？",
    "options": [],
    "answer": "(-3,3)"
  },
  {
    "id": "a053",
    "type": "math",
    "topic": "機率",
    "question": "有一個摸彩活動，共有和人數相同數量的彩球，其中獎項為5000元禮券及8000元禮券有各5顆，每顆球被抽中的機率皆相同，抽後不放回。已知中獎機率為0.4%。前100位參加抽獎者，有1人抽中5000元且沒有人抽中8000元，則第101號可獲禮券金額的期望值為幾元？",
    "options": [],
    "answer": "25"
  },
  {
    "id": "a054",
    "type": "math",
    "topic": "平面向量",
    "question": "坐標平面上，已知向量v在向量(2, -3)方向的正射影長比原長少1，而在向量(3,2)方向的正射影長比原長少2。若v與兩向量(2, -3),(3, 2)的夾角皆為銳角，v在向量(4,7)方向的正射影長為(a√b)/c，則(a,b,c) = ?",
    "options": [],
    "answer": "(2,5,5)"
  },
  {
    "id": "a055",
    "type": "math",
    "topic": "不等式",
    "question": "座標平面上，在以O(0, 0),A(0, 1),B(1, 1),C(1, 0)為頂點的正方形內，令R為滿足下述條件的點P(x, y)所成區域：與點P(x, y)的距離為|x-y|之所有點所成圖形完全落在正方形OABC（含邊界）內。則區域R的面積為？（化為最簡分數）",
    "options": [],
    "answer": "1/3"
  }
]